flbenchmark/__init__.py
flbenchmark/__main__.py
flbenchmark/datasets/__init__.py
flbenchmark/datasets/dataset.py
flbenchmark/datasets/fate.py
flbenchmark/datasets/flbdatasets.py
flbenchmark/datasets/leaf.py
flbenchmark/datasets/utils.py
flbenchmark/logging/__init__.py
flbenchmark/logging/common.py
flbenchmark/logging/logger.py
flbenchmark/logging/report.py
flbenchmark-0.1.3.dist-info/LICENSE
flbenchmark-0.1.3.dist-info/METADATA
flbenchmark-0.1.3.dist-info/WHEEL
flbenchmark-0.1.3.dist-info/top_level.txt
flbenchmark-0.1.3.dist-info/RECORD
